linktap/LinkTap.py
linktap/__init__.py
linktap/errors.py
linktap/linktap.py
linktap-0.0.6.dist-info/LICENSE
linktap-0.0.6.dist-info/METADATA
linktap-0.0.6.dist-info/WHEEL
linktap-0.0.6.dist-info/top_level.txt
linktap-0.0.6.dist-info/RECORD
