Metadata-Version: 2.1
Name: linktap
Version: 0.0.6
Summary: Linktap API Python library
Home-page: https://github.com/dearlove/python-linktap
Author: Andrew Dearlove
Author-email: git@dearlove.email
License: UNKNOWN
Project-URL: Bug Tracker, https://github.com/dearlove/python-linktap/issues
Platform: UNKNOWN
Classifier: Programming Language :: Python :: 3
Classifier: License :: OSI Approved :: MIT License
Classifier: Operating System :: OS Independent
Requires-Python: >=3.6
Requires-Dist: requests
